[
  { "name": "Peach", "max": 99.37, "min": 5.33, "avr": 54.372449799196765 },
  { "name": "Orange", "max": 99.93, "min": 5.12, "avr": 52.80708860759496 },
  { "name": "Apple", "max": 99.44, "min": 5.53, "avr": 53.520599999999995 },
  { "name": "Strawberry", "max": 99.37, "min": 5.2, "avr": 52.946602316602316 },
  { "name": "Apricot", "max": 99.81, "min": 5.12, "avr": 50.51109756097566 },
  { "name": "Mango", "max": 99.89, "min": 5.79, "avr": 54.51681102362206 },
  { "name": "Raspberry", "max": 99.97, "min": 5.05, "avr": 51.9449429657795 },
  { "name": "Plum", "max": 99.36, "min": 5.07, "avr": 52.65092307692308 },
  { "name": "Banana", "max": 99.98, "min": 5.1, "avr": 50.440902527075835 },
  { "name": "Blueberry", "max": 99.77, "min": 5.43, "avr": 55.45782786885245 },
  { "name": "Cherry", "max": 99.51, "min": 5.6, "avr": 53.84628906250001 },
  { "name": "Grapes", "max": 99.87, "min": 5.37, "avr": 52.688641975308634 },
  { "name": "Papaya", "max": 98.95, "min": 5.2, "avr": 50.92202586206898 },
  { "name": "Boysenberry", "max": 99.9, "min": 5.6, "avr": 52.95119402985074 },
  { "name": "Melon", "max": 99.83, "min": 5.08, "avr": 50.922335766423316 },
  { "name": "Guava", "max": 99.95, "min": 5.18, "avr": 52.27559999999999 },
  { "name": "Blackberry", "max": 99.61, "min": 5.02, "avr": 52.59899193548387 },
  { "name": "Cranberry", "max": 99.82, "min": 6.65, "avr": 54.64344129554657 },
  { "name": "Kiwifruit", "max": 99.8, "min": 5.99, "avr": 51.1655947136564 },
  { "name": "Pineapple", "max": 99.66, "min": 5.13, "avr": 51.58453488372091 }
]
